thriftpy2_httpx_client/__init__.py
thriftpy2_httpx_client/_version.py
thriftpy2_httpx_client/aio/__init__.py
thriftpy2_httpx_client/aio/rpc.py
thriftpy2_httpx_client/aio/transport.py
thriftpy2_httpx_client/sync/__init__.py
thriftpy2_httpx_client/sync/rpc.py
thriftpy2_httpx_client/sync/transport.py
thriftpy2_httpx_client-0.5.dist-info/LICENSE
thriftpy2_httpx_client-0.5.dist-info/METADATA
thriftpy2_httpx_client-0.5.dist-info/WHEEL
thriftpy2_httpx_client-0.5.dist-info/top_level.txt
thriftpy2_httpx_client-0.5.dist-info/RECORD
