Metadata-Version: 2.1
Name: thriftpy2-httpx-client
Version: 0.5
Summary: HTTPX Client for ThriftPy2
Home-page: https://github.com/aiudirog/ThriftPy2-HTTPX-Client
Author: Roger Aiudi
Author-email: aiudirog@gmail.com
License: MIT
Keywords: thrift,async,asyncio,httpx
Classifier: Development Status :: 5 - Production/Stable
Classifier: Intended Audience :: Developers
Classifier: License :: OSI Approved :: MIT License
Classifier: Programming Language :: Python :: 3.9
Classifier: Programming Language :: Python :: 3.10
Classifier: Programming Language :: Python :: 3.11
Classifier: Programming Language :: Python :: 3.12
Classifier: Programming Language :: Python :: 3.13
Classifier: Programming Language :: Python :: Implementation :: CPython
Classifier: Programming Language :: Python :: Implementation :: PyPy
Classifier: Topic :: Software Development :: Libraries :: Python Modules
Requires-Python: >=3.7
License-File: LICENSE
Requires-Dist: thriftpy2>=0.4.11
Requires-Dist: httpx<0.29,>=0.16
Provides-Extra: test
Requires-Dist: pytest; extra == "test"
Requires-Dist: pytest-asyncio; extra == "test"
Requires-Dist: urllib3; extra == "test"
Provides-Extra: all
Requires-Dist: pytest; extra == "all"
Requires-Dist: pytest-asyncio; extra == "all"
Requires-Dist: urllib3; extra == "all"
